evm_cfg_builder/__init__.py
evm_cfg_builder/__main__.py
evm_cfg_builder/cfg/__init__.py
evm_cfg_builder/cfg/basic_block.py
evm_cfg_builder/cfg/cfg.py
evm_cfg_builder/cfg/function.py
evm_cfg_builder/known_hashes/__init__.py
evm_cfg_builder/known_hashes/download_sigs.py
evm_cfg_builder/known_hashes/known_hashes.py
evm_cfg_builder/value_analysis/__init__.py
evm_cfg_builder/value_analysis/value_set_analysis.py
python_tests/__init__.py
python_tests/value_set_analysis.py
evm_cfg_builder_fixed-0.3.1.dist-info/LICENSE
evm_cfg_builder_fixed-0.3.1.dist-info/METADATA
evm_cfg_builder_fixed-0.3.1.dist-info/WHEEL
evm_cfg_builder_fixed-0.3.1.dist-info/entry_points.txt
evm_cfg_builder_fixed-0.3.1.dist-info/top_level.txt
evm_cfg_builder_fixed-0.3.1.dist-info/RECORD
