Metadata-Version: 2.1
Name: evm-cfg-builder-fixed
Version: 0.3.1
Summary: EVM cfg builder written in Python 3. Infinite loop error fixed by Soptq.
Home-page: https://github.com/Soptq/evm_cfg_builder
Author: Soptq
License: AGPL-3.0
Requires-Python: >=3.6
License-File: LICENSE
Requires-Dist: pyevmasm >=0.1.1
Requires-Dist: crytic-compile >=0.1.13
